pyzeversolar/__init__.py
pyzeversolar-0.0.5.dist-info/LICENSE
pyzeversolar-0.0.5.dist-info/METADATA
pyzeversolar-0.0.5.dist-info/WHEEL
pyzeversolar-0.0.5.dist-info/top_level.txt
pyzeversolar-0.0.5.dist-info/RECORD
