Metadata-Version: 2.1
Name: pyzeversolar
Version: 0.0.5
Summary: Library to communicate with ZeverSolar inverters
Home-page: https://github.com/brahmah/pyzeversolar
Author: brahmah
Author-email: brahmah90@gmail.com
License: UNKNOWN
Platform: UNKNOWN
Classifier: Programming Language :: Python :: 3
Classifier: License :: OSI Approved :: Apache Software License
Classifier: Operating System :: OS Independent
Requires-Python: >=3.6
License-File: LICENSE
